[
  {
    "correct_answer": "The bicycle is a two-wheeled vehicle propelled by human power.",
    "retrieved_context": "name: Draisine\ntype: Vehicle\ndescription: A two-wheeled vehicle invented by Baron Karl von Drais in the early 19th century, propelled by the rider pushing off the ground with their feet. name: electric bikes\ntype: Bicycle Type\ndescription: Electric bikes are bicycles equipped with an electric motor to assist the rider, providing easier riding and longer distances. name: Racing Bikes\ntype: Bicycle Type\ndescription: High-performance bicycles designed for speed and competition. name: Transportation\ntype: Activity\ndescription: Using bicycles as a means of transportation for short and long distances. name: Recreation\ntype: Activity\ndescription: Engaging in leisure activities such as cycling for fun or exercise. name: Racing\ntype: Activity\ndescription: Competitive cycling events where participants race against each other. name: rear wheel\ntype: Bicycle Component\ndescription: The rear wheel of a bicycle is one of the two wheels that support and propel the vehicle. It can vary in size and design depending on the type of bicycle. name: bicycles\ntype: Transportation Mode\ndescription: Bicycles are two-wheeled vehicles used for transportation, exercise, and leisure. name: bicycle\ntype: Transportation Mode\ndescription: A bicycle is a human-powered or motor-assisted vehicle with two wheels, used for transportation and recreation. name: High-Wheel Bicycle (Penny-Farthing)\ntype: Bicycle Type\ndescription: The high-wheel bicycle, also known as the penny-farthing, was a significant milestone in the evolution of bicycles. It featured a large front wheel and a much smaller rear wheel. name: Front Wheel\ntype: Bicycle Component\ndescription: The front wheel of a bicycle, which can vary in size and design depending on the type of bicycle. name: Wooden Contraption\ntype: Historical Object\ndescription: An early form of the bicycle made from wood. name: Penny-Farthing\ntype: Vehicle\ndescription: A distinctive bicycle with a large front wheel and a smaller rear wheel, known for its speed and elegance but also dangerous due to its high center of gravity. name: Baron Karl von Drais\ntype: Person\ndescription: Baron Karl von Drais was a German inventor who created the draisine, an early version of the bicycle. name: Safety Bicycle\ntype: Vehicle\ndescription: A bicycle with two wheels of equal size, a chain drive system, and pneumatic tires, making it more stable, comfortable, and efficient. name: cyclists\ntype: Rider Group\ndescription: Cyclists are individuals who ride bicycles for various purposes such as commuting, exercise, and leisure. name: Cruisers\ntype: Bicycle Type\ndescription: Comfortable bicycles designed for leisure and casual riding. name: Culture\ntype: Sector\ndescription: The arts, customs, and habits that characterize a particular society or nation. name: Bicycle\ntype: Vehicle\ndescription: A two-wheeled vehicle propelled by human power, with a rich history of evolution and innovation that spans centuries. name: recent years\ntype: Time Period\ndescription: Recent years refer to the most recent period in time, typically within the last few decades. name: Velocipede (Boneshaker)\ntype: Vehicle\ndescription: An early bicycle with pedals attached directly to the front wheel, offering a smoother ride and greater speed than the draisine. name: Cycling\ntype: Activity\ndescription: Cycling, the activity of riding bicycles, has evolved from a simple wooden contraption to a high-tech racing machine. It has had a profound impact on society, influencing transportation, recreation, and culture. name: Tour de France\ntype: Cycling Race\ndescription: The Tour de France is one of the most prestigious and challenging professional cycling races in the world, showcasing the speed, skill, and endurance of elite cyclists. name: Penny-Farthing Bicycle\ntype: Bicycle Type\ndescription: A distinctive bicycle featuring a large front wheel and a smaller rear wheel, giving it a high center of gravity and a precarious ride. name: 19th century\ntype: Time Period\ndescription: The 19th century spans from the year 1801 to 1900. It was a period of significant technological and social change, including major advancements in transportation and communication. name: Commuting\ntype: Activity\ndescription: Traveling between home and work or school.",
    "evaluation": 1
  },
  {
    "correct_answer": "The earliest known prototype of the bicycle was called the 'draisine'.",
    "retrieved_context": "name: safety bicycle\ntype: Bicycle Type\ndescription: The safety bicycle featured two wheels of equal size, a chain drive system, and pneumatic tires, making it more stable, comfortable, and efficient than its predecessors. name: boneshaker\ntype: Bicycle Type\ndescription: The boneshaker, also known as the velocipede, was an early bicycle that featured pedals attached directly to the front wheel. It offered a smoother ride and greater speed compared to its predecessor, the draisine, but it was still heavy and cumbersome, making it difficult to maneuver on rough terrain. name: Racing\ntype: Activity\ndescription: Competitive cycling events where participants race against each other. name: draisine\ntype: Bicycle Type\ndescription: The draisine was an early wooden bicycle without pedals, propelled by the rider pushing along the ground with their feet. name: Velocipede (Boneshaker)\ntype: Vehicle\ndescription: An early bicycle with pedals attached directly to the front wheel, offering a smoother ride and greater speed than the draisine. name: Draisine\ntype: Vehicle\ndescription: A two-wheeled vehicle invented by Baron Karl von Drais in the early 19th century, propelled by the rider pushing off the ground with their feet. name: Penny-Farthing\ntype: Vehicle\ndescription: A distinctive bicycle with a large front wheel and a smaller rear wheel, known for its speed and elegance but also dangerous due to its high center of gravity. name: Evolution of the Bicycle\ntype: Historical Process\ndescription: The evolution of the bicycle is a historical process that spans centuries, from its early wooden contraptions to modern high-tech racing machines. name: Bicycle\ntype: Vehicle\ndescription: A two-wheeled vehicle propelled by human power, with a rich history of evolution and innovation that spans centuries. name: evolution of the bicycle\ntype: Process\ndescription: The evolution of the bicycle from a wooden contraption to a high-tech racing machine. name: Safety Bicycle\ntype: Vehicle\ndescription: A bicycle with two wheels of equal size, a chain drive system, and pneumatic tires, making it more stable, comfortable, and efficient. name: Penny-Farthing Bicycle\ntype: Bicycle Type\ndescription: A distinctive bicycle featuring a large front wheel and a smaller rear wheel, giving it a high center of gravity and a precarious ride. name: Transportation\ntype: Activity\ndescription: Using bicycles as a means of transportation for short and long distances. name: Bicycle Evolution\ntype: Technological Development\ndescription: The evolution of the bicycle has been a continuous process, with advancements in materials, design, and technology throughout the 20th century. name: Recreation\ntype: Activity\ndescription: Engaging in leisure activities such as cycling for fun or exercise. name: Commuting\ntype: Activity\ndescription: Traveling between home and work or school.",
    "evaluation": 1
  },
  {
    "correct_answer": "The draisine had no pedals and was propelled by the rider pushing off the ground with their feet.",
    "retrieved_context": "name: Front Wheel\ntype: Bicycle Component\ndescription: The front wheel of a bicycle, which can vary in size and design depending on the type of bicycle. name: Racing\ntype: Activity\ndescription: Competitive cycling events where participants race against each other. name: draisine\ntype: Bicycle Type\ndescription: The draisine was an early wooden bicycle without pedals, propelled by the rider pushing along the ground with their feet. name: Velocipede (Boneshaker)\ntype: Vehicle\ndescription: An early bicycle with pedals attached directly to the front wheel, offering a smoother ride and greater speed than the draisine. name: Draisine\ntype: Vehicle\ndescription: A two-wheeled vehicle invented by Baron Karl von Drais in the early 19th century, propelled by the rider pushing off the ground with their feet. name: Penny-Farthing\ntype: Vehicle\ndescription: A distinctive bicycle with a large front wheel and a smaller rear wheel, known for its speed and elegance but also dangerous due to its high center of gravity. name: bicycles\ntype: Transportation Mode\ndescription: Bicycles are two-wheeled vehicles used for transportation, exercise, and leisure. name: rear wheel\ntype: Bicycle Component\ndescription: The rear wheel of a bicycle is one of the two wheels that support and propel the vehicle. It can vary in size and design depending on the type of bicycle. name: Bicycle\ntype: Vehicle\ndescription: A two-wheeled vehicle propelled by human power, with a rich history of evolution and innovation that spans centuries. name: Baron Karl von Drais\ntype: Person\ndescription: Baron Karl von Drais was a German inventor who created the draisine, an early version of the bicycle. name: Safety Bicycle\ntype: Vehicle\ndescription: A bicycle with two wheels of equal size, a chain drive system, and pneumatic tires, making it more stable, comfortable, and efficient. name: Penny-Farthing Bicycle\ntype: Bicycle Type\ndescription: A distinctive bicycle featuring a large front wheel and a smaller rear wheel, giving it a high center of gravity and a precarious ride. name: Transportation\ntype: Activity\ndescription: Using bicycles as a means of transportation for short and long distances. name: 19th century\ntype: Time Period\ndescription: The 19th century spans from the year 1801 to 1900. It was a period of significant technological and social change, including major advancements in transportation and communication. name: High-Wheel Bicycle (Penny-Farthing)\ntype: Bicycle Type\ndescription: The high-wheel bicycle, also known as the penny-farthing, was a significant milestone in the evolution of bicycles. It featured a large front wheel and a much smaller rear wheel. name: Recreation\ntype: Activity\ndescription: Engaging in leisure activities such as cycling for fun or exercise. name: Commuting\ntype: Activity\ndescription: Traveling between home and work or school.",
    "evaluation": 1
  },
  {
    "correct_answer": "The velocipede, also known as the 'boneshaker', featured pedals attached directly to the front wheel.",
    "retrieved_context": "name: Front Wheel\ntype: Bicycle Component\ndescription: The front wheel of a bicycle, which can vary in size and design depending on the type of bicycle. name: Racing\ntype: Activity\ndescription: Competitive cycling events where participants race against each other. name: rear wheel\ntype: Bicycle Component\ndescription: The rear wheel of a bicycle is one of the two wheels that support and propel the vehicle. It can vary in size and design depending on the type of bicycle. name: Velocipede (Boneshaker)\ntype: Vehicle\ndescription: An early bicycle with pedals attached directly to the front wheel, offering a smoother ride and greater speed than the draisine. name: Draisine\ntype: Vehicle\ndescription: A two-wheeled vehicle invented by Baron Karl von Drais in the early 19th century, propelled by the rider pushing off the ground with their feet. name: Penny-Farthing\ntype: Vehicle\ndescription: A distinctive bicycle with a large front wheel and a smaller rear wheel, known for its speed and elegance but also dangerous due to its high center of gravity. name: velocipede (boneshaker)\ntype: Bicycle Model\ndescription: The velocipede, also known as the \"boneshaker,\" was an early bicycle with pedals attached directly to the front wheel. It allowed riders to propel themselves forward by turning the pedals in a circular motion. name: Bicycle\ntype: Vehicle\ndescription: A two-wheeled vehicle propelled by human power, with a rich history of evolution and innovation that spans centuries. name: Pedals (in early designs)\ntype: Bicycle Component\ndescription: Components that allow the rider to propel the bicycle by turning them in a circular motion. name: Safety Bicycle\ntype: Vehicle\ndescription: A bicycle with two wheels of equal size, a chain drive system, and pneumatic tires, making it more stable, comfortable, and efficient. name: Baron Karl von Drais\ntype: Person\ndescription: Baron Karl von Drais was a German inventor who created the draisine, an early version of the bicycle. name: Penny-Farthing Bicycle\ntype: Bicycle Type\ndescription: A distinctive bicycle featuring a large front wheel and a smaller rear wheel, giving it a high center of gravity and a precarious ride. name: Transportation\ntype: Activity\ndescription: Using bicycles as a means of transportation for short and long distances. name: 19th century\ntype: Time Period\ndescription: The 19th century spans from the year 1801 to 1900. It was a period of significant technological and social change, including major advancements in transportation and communication. name: Cruisers\ntype: Bicycle Type\ndescription: Comfortable bicycles designed for leisure and casual riding. name: High-Wheel Bicycle (Penny-Farthing)\ntype: Bicycle Type\ndescription: The high-wheel bicycle, also known as the penny-farthing, was a significant milestone in the evolution of bicycles. It featured a large front wheel and a much smaller rear wheel. name: Recreation\ntype: Activity\ndescription: Engaging in leisure activities such as cycling for fun or exercise. name: Commuting\ntype: Activity\ndescription: Traveling between home and work or school.",
    "evaluation": 1
  },
  {
    "correct_answer": "The boneshaker offered a smoother ride and greater speed compared to the draisine.",
    "retrieved_context": "name: boneshaker\ntype: Bicycle Type\ndescription: The boneshaker, also known as the velocipede, was an early bicycle that featured pedals attached directly to the front wheel. It offered a smoother ride and greater speed compared to its predecessor, the draisine, but it was still heavy and cumbersome, making it difficult to maneuver on rough terrain. name: draisine\ntype: Bicycle Type\ndescription: The draisine was an early wooden bicycle without pedals, propelled by the rider pushing along the ground with their feet. name: Draisine\ntype: Vehicle\ndescription: A two-wheeled vehicle invented by Baron Karl von Drais in the early 19th century, propelled by the rider pushing off the ground with their feet. name: Transportation\ntype: Activity\ndescription: Using bicycles as a means of transportation for short and long distances. name: Recreation\ntype: Activity\ndescription: Engaging in leisure activities such as cycling for fun or exercise. name: Racing\ntype: Activity\ndescription: Competitive cycling events where participants race against each other. name: rear wheel\ntype: Bicycle Component\ndescription: The rear wheel of a bicycle is one of the two wheels that support and propel the vehicle. It can vary in size and design depending on the type of bicycle. name: velocipede (boneshaker)\ntype: Bicycle Model\ndescription: The velocipede, also known as the \"boneshaker,\" was an early bicycle with pedals attached directly to the front wheel. It allowed riders to propel themselves forward by turning the pedals in a circular motion. name: High-Wheel Bicycle (Penny-Farthing)\ntype: Bicycle Type\ndescription: The high-wheel bicycle, also known as the penny-farthing, was a significant milestone in the evolution of bicycles. It featured a large front wheel and a much smaller rear wheel. name: Front Wheel\ntype: Bicycle Component\ndescription: The front wheel of a bicycle, which can vary in size and design depending on the type of bicycle. name: safety bicycle\ntype: Bicycle Type\ndescription: The safety bicycle featured two wheels of equal size, a chain drive system, and pneumatic tires, making it more stable, comfortable, and efficient than its predecessors. name: Penny-Farthing\ntype: Vehicle\ndescription: A distinctive bicycle with a large front wheel and a smaller rear wheel, known for its speed and elegance but also dangerous due to its high center of gravity. name: Baron Karl von Drais\ntype: Person\ndescription: Baron Karl von Drais was a German inventor who created the draisine, an early version of the bicycle. name: Safety Bicycle\ntype: Vehicle\ndescription: A bicycle with two wheels of equal size, a chain drive system, and pneumatic tires, making it more stable, comfortable, and efficient. name: Cruisers\ntype: Bicycle Type\ndescription: Comfortable bicycles designed for leisure and casual riding. name: Bicycle\ntype: Vehicle\ndescription: A two-wheeled vehicle propelled by human power, with a rich history of evolution and innovation that spans centuries. name: Velocipede (Boneshaker)\ntype: Vehicle\ndescription: An early bicycle with pedals attached directly to the front wheel, offering a smoother ride and greater speed than the draisine. name: Penny-Farthing Bicycle\ntype: Bicycle Type\ndescription: A distinctive bicycle featuring a large front wheel and a smaller rear wheel, giving it a high center of gravity and a precarious ride. name: 19th century\ntype: Time Period\ndescription: The 19th century spans from the year 1801 to 1900. It was a period of significant technological and social change, including major advancements in transportation and communication. name: Commuting\ntype: Activity\ndescription: Traveling between home and work or school.",
    "evaluation": 1
  },
  {
    "correct_answer": "The high-wheel bicycle, or penny-farthing, had a large front wheel and a smaller rear wheel.",
    "retrieved_context": "name: penny-farthing\ntype: Bicycle Type\ndescription: A type of bicycle with a large front wheel and a much smaller rear wheel, popular in the late 19th century. name: Draisine\ntype: Vehicle\ndescription: A two-wheeled vehicle invented by Baron Karl von Drais in the early 19th century, propelled by the rider pushing off the ground with their feet. name: Pedals (in early designs)\ntype: Bicycle Component\ndescription: Components that allow the rider to propel the bicycle by turning them in a circular motion. name: Transportation\ntype: Activity\ndescription: Using bicycles as a means of transportation for short and long distances. name: Recreation\ntype: Activity\ndescription: Engaging in leisure activities such as cycling for fun or exercise. name: Racing\ntype: Activity\ndescription: Competitive cycling events where participants race against each other. name: rear wheel\ntype: Bicycle Component\ndescription: The rear wheel of a bicycle is one of the two wheels that support and propel the vehicle. It can vary in size and design depending on the type of bicycle. name: High-Wheel Bicycle (Penny-Farthing)\ntype: Bicycle Type\ndescription: The high-wheel bicycle, also known as the penny-farthing, was a significant milestone in the evolution of bicycles. It featured a large front wheel and a much smaller rear wheel. name: Front Wheel\ntype: Bicycle Component\ndescription: The front wheel of a bicycle, which can vary in size and design depending on the type of bicycle. name: Rear Wheel (in high-wheel designs)\ntype: Bicycle Component\ndescription: The rear wheel of a bicycle, which can vary in size depending on the type of bicycle. name: Penny-Farthing\ntype: Vehicle\ndescription: A distinctive bicycle with a large front wheel and a smaller rear wheel, known for its speed and elegance but also dangerous due to its high center of gravity. name: Baron Karl von Drais\ntype: Person\ndescription: Baron Karl von Drais was a German inventor who created the draisine, an early version of the bicycle. name: Safety Bicycle\ntype: Vehicle\ndescription: A bicycle with two wheels of equal size, a chain drive system, and pneumatic tires, making it more stable, comfortable, and efficient. name: Bicycle\ntype: Vehicle\ndescription: A two-wheeled vehicle propelled by human power, with a rich history of evolution and innovation that spans centuries. name: Rear Wheel (in safety bicycles)\ntype: Bicycle Component\ndescription: The rear wheel of a bicycle, which can vary in size depending on the type of bicycle. name: Velocipede (Boneshaker)\ntype: Vehicle\ndescription: An early bicycle with pedals attached directly to the front wheel, offering a smoother ride and greater speed than the draisine. name: front wheel\ntype: Bicycle Component\ndescription: The front wheel of a bicycle is one of the two wheels that support and propel the vehicle. It can vary in size and design depending on the type of bicycle. name: Penny-Farthing Bicycle\ntype: Bicycle Type\ndescription: A distinctive bicycle featuring a large front wheel and a smaller rear wheel, giving it a high center of gravity and a precarious ride. name: 19th century\ntype: Time Period\ndescription: The 19th century spans from the year 1801 to 1900. It was a period of significant technological and social change, including major advancements in transportation and communication. name: Commuting\ntype: Activity\ndescription: Traveling between home and work or school.",
    "evaluation": 1
  },
  {
    "correct_answer": "The safety bicycle featured two wheels of equal size, a chain drive system, and pneumatic tires.",
    "retrieved_context": "name: draisine\ntype: Bicycle Type\ndescription: The draisine was an early wooden bicycle without pedals, propelled by the rider pushing along the ground with their feet. name: Draisine\ntype: Vehicle\ndescription: A two-wheeled vehicle invented by Baron Karl von Drais in the early 19th century, propelled by the rider pushing off the ground with their feet. name: Transportation\ntype: Activity\ndescription: Using bicycles as a means of transportation for short and long distances. name: Recreation\ntype: Activity\ndescription: Engaging in leisure activities such as cycling for fun or exercise. name: Racing\ntype: Activity\ndescription: Competitive cycling events where participants race against each other. name: rear wheel\ntype: Bicycle Component\ndescription: The rear wheel of a bicycle is one of the two wheels that support and propel the vehicle. It can vary in size and design depending on the type of bicycle. name: cruiser bicycles\ntype: Bicycle Style\ndescription: Cruiser bicycles are designed for comfort and leisure, often featuring wide tires, a relaxed geometry, and upright seating positions. name: High-Wheel Bicycle (Penny-Farthing)\ntype: Bicycle Type\ndescription: The high-wheel bicycle, also known as the penny-farthing, was a significant milestone in the evolution of bicycles. It featured a large front wheel and a much smaller rear wheel. name: Front Wheel\ntype: Bicycle Component\ndescription: The front wheel of a bicycle, which can vary in size and design depending on the type of bicycle. name: safety bicycle\ntype: Bicycle Type\ndescription: The safety bicycle featured two wheels of equal size, a chain drive system, and pneumatic tires, making it more stable, comfortable, and efficient than its predecessors. name: Penny-Farthing\ntype: Vehicle\ndescription: A distinctive bicycle with a large front wheel and a smaller rear wheel, known for its speed and elegance but also dangerous due to its high center of gravity. name: Baron Karl von Drais\ntype: Person\ndescription: Baron Karl von Drais was a German inventor who created the draisine, an early version of the bicycle. name: Safety Bicycle\ntype: Vehicle\ndescription: A bicycle with two wheels of equal size, a chain drive system, and pneumatic tires, making it more stable, comfortable, and efficient. name: Bicycle\ntype: Vehicle\ndescription: A two-wheeled vehicle propelled by human power, with a rich history of evolution and innovation that spans centuries. name: Rear Wheel (in safety bicycles)\ntype: Bicycle Component\ndescription: The rear wheel of a bicycle, which can vary in size depending on the type of bicycle. name: Velocipede (Boneshaker)\ntype: Vehicle\ndescription: An early bicycle with pedals attached directly to the front wheel, offering a smoother ride and greater speed than the draisine. name: Penny-Farthing Bicycle\ntype: Bicycle Type\ndescription: A distinctive bicycle featuring a large front wheel and a smaller rear wheel, giving it a high center of gravity and a precarious ride. name: 19th century\ntype: Time Period\ndescription: The 19th century spans from the year 1801 to 1900. It was a period of significant technological and social change, including major advancements in transportation and communication. name: Commuting\ntype: Activity\ndescription: Traveling between home and work or school.",
    "evaluation": 1
  },
  {
    "correct_answer": "The safety bicycle was more stable, comfortable, and efficient than its predecessors.",
    "retrieved_context": "name: future\ntype: Concept\ndescription: The future refers to the time that is yet to come, encompassing potential advancements and developments in various fields. name: safety bicycle\ntype: Bicycle Type\ndescription: The safety bicycle featured two wheels of equal size, a chain drive system, and pneumatic tires, making it more stable, comfortable, and efficient than its predecessors. name: Bicycle Design and Technology\ntype: Technological Advancement\ndescription: Throughout the 20th century, bicycles continued to evolve with advancements in materials, design, and technology. name: Bicycle Innovations\ntype: Technological Advancements\ndescription: Innovations in bicycle design and technology have included improvements in materials, mechanics, and aerodynamics. name: Racing\ntype: Activity\ndescription: Competitive cycling events where participants race against each other. name: Velocipede (Boneshaker)\ntype: Vehicle\ndescription: An early bicycle with pedals attached directly to the front wheel, offering a smoother ride and greater speed than the draisine. name: Draisine\ntype: Vehicle\ndescription: A two-wheeled vehicle invented by Baron Karl von Drais in the early 19th century, propelled by the rider pushing off the ground with their feet. name: Penny-Farthing\ntype: Vehicle\ndescription: A distinctive bicycle with a large front wheel and a smaller rear wheel, known for its speed and elegance but also dangerous due to its high center of gravity. name: Bicycle\ntype: Vehicle\ndescription: A two-wheeled vehicle propelled by human power, with a rich history of evolution and innovation that spans centuries. name: Safety Bicycle\ntype: Vehicle\ndescription: A bicycle with two wheels of equal size, a chain drive system, and pneumatic tires, making it more stable, comfortable, and efficient. name: evolution of the bicycle\ntype: Process\ndescription: The evolution of the bicycle from a wooden contraption to a high-tech racing machine. name: cruiser bicycles\ntype: Bicycle Style\ndescription: Cruiser bicycles are designed for comfort and leisure, often featuring wide tires, a relaxed geometry, and upright seating positions. name: Transportation\ntype: Activity\ndescription: Using bicycles as a means of transportation for short and long distances. name: Bicycle Evolution\ntype: Technological Development\ndescription: The evolution of the bicycle has been a continuous process, with advancements in materials, design, and technology throughout the 20th century. name: Recreation\ntype: Activity\ndescription: Engaging in leisure activities such as cycling for fun or exercise. name: Commuting\ntype: Activity\ndescription: Traveling between home and work or school.",
    "evaluation": 1
  },
  {
    "correct_answer": "Steel became the primary material used in bicycle frames in the early 1900s.",
    "retrieved_context": "name: Carbon Fiber Frames\ntype: Material\ndescription: Carbon fiber is a lightweight, strong, and aerodynamic material used in the construction of high-performance bicycles. name: Bicycle Design and Technology\ntype: Technological Advancement\ndescription: Throughout the 20th century, bicycles continued to evolve with advancements in materials, design, and technology. name: Evolution of the Bicycle\ntype: Historical Process\ndescription: The evolution of the bicycle is a historical process that spans centuries, from its early wooden contraptions to modern high-tech racing machines. name: 20th century\ntype: Time Period\ndescription: The 20th century spans from the year 1901 to 2000 and is marked by significant advancements in technology, materials science, and societal changes. name: evolution of the bicycle\ntype: Process\ndescription: The evolution of the bicycle from a wooden contraption to a high-tech racing machine. name: Aluminum and Titanium in Bicycle Construction\ntype: Material Innovation\ndescription: Aluminum and titanium emerged as popular alternatives to steel, providing lighter weight and increased stiffness for improved performance. name: Carbon Fiber in Bicycle Construction\ntype: Material Innovation\ndescription: Carbon fiber was introduced as a revolutionary material, providing significant improvements in weight reduction and stiffness. name: bicycle frames\ntype: Product Component\ndescription: Bicycle frames are the main structural components of bicycles, providing support and stability. name: Bicycle Evolution\ntype: Technological Development\ndescription: The evolution of the bicycle has been a continuous process, with advancements in materials, design, and technology throughout the 20th century. name: Bicycle Frames\ntype: Product Component\ndescription: Bicycle frames are the structural components of bicycles that provide support and stability.",
    "evaluation": 0
  },
  {
    "correct_answer": "Aluminum and titanium emerged as popular alternatives to steel in the mid-20th century.",
    "retrieved_context": "name: Carbon Fiber\ntype: Material\ndescription: Carbon fiber is a composite material known for its lightweight, strength, and aerodynamic properties. name: Steel\ntype: Material\ndescription: Steel is a strong and durable material that became the primary choice for bicycle frames in the early 1900s due to its reasonable cost. name: Technological Advancements\ntype: Process\ndescription: Advancements in technology have played a crucial role in the development of modern bicycles. name: Aluminum\ntype: Material\ndescription: Aluminum is a lightweight metal used in various applications, including bicycle frames. name: Design Evolution\ntype: Process\ndescription: The design of bicycles has evolved over time to meet the changing needs and preferences of riders. name: steel\ntype: Material\ndescription: Steel is an alloy of iron and carbon, known for its strength and durability. It has been widely used in various applications, including bicycle frames. name: Titanium\ntype: Material\ndescription: Titanium is a strong, lightweight metal used in high-performance applications, including bicycle frames. name: bicycle manufacturing\ntype: Industry\ndescription: Bicycle manufacturing involves the production of bicycles, from early wooden contraptions to modern high-tech racing machines. The industry has evolved significantly with advancements in materials, design, and technology. name: Aluminum and Titanium in Bicycle Construction\ntype: Material Innovation\ndescription: Aluminum and titanium emerged as popular alternatives to steel, providing lighter weight and increased stiffness for improved performance. name: bicycle frames\ntype: Product Component\ndescription: Bicycle frames are the main structural components of bicycles, providing support and stability. name: titanium\ntype: Material\ndescription: Titanium is a strong, lightweight, and corrosion-resistant metal that emerged as a popular alternative to steel in the mid-20th century for bicycle frames. name: aluminum\ntype: Material\ndescription: Aluminum is a lightweight and stiff material that emerged as an alternative to steel in the mid-20th century, providing improved performance for various applications. name: Bicycle Frames\ntype: Product Component\ndescription: Bicycle frames are the structural components of bicycles that provide support and stability.",
    "evaluation": 1
  },
  {
    "correct_answer": "Carbon fiber frames are lightweight, strong, and aerodynamic.",
    "retrieved_context": "name: Elite Cyclists\ntype: Athlete\ndescription: Elite cyclists are highly skilled and physically fit athletes who compete at the highest levels of professional cycling. name: Racing Bikes\ntype: Bicycle Type\ndescription: High-performance bicycles designed for speed and competition. name: Transportation\ntype: Activity\ndescription: Using bicycles as a means of transportation for short and long distances. name: Late 20th Century\ntype: Time Period\ndescription: The late 20th century refers to the period from approximately 1970 to 1999. name: bicycle frames\ntype: Product Component\ndescription: Bicycle frames are the main structural components of bicycles, providing support and stability. name: High-performance cycling\ntype: Activity\ndescription: High-performance cycling involves the use of advanced materials and designs to achieve optimal speed, agility, and responsiveness in competitive racing. name: cruisers\ntype: Bicycle Style\ndescription: Cruisers are a type of bicycle designed for comfort and leisure, featuring upright seating positions and often wider tires. name: aluminum\ntype: Material\ndescription: Aluminum is a lightweight and stiff material that emerged as an alternative to steel in the mid-20th century, providing improved performance for various applications. name: Recreation\ntype: Activity\ndescription: Engaging in leisure activities such as cycling for fun or exercise. name: Carbon Fiber Frames\ntype: Material\ndescription: Carbon fiber is a lightweight, strong, and aerodynamic material used in the construction of high-performance bicycles. name: carbon fiber\ntype: Material\ndescription: Carbon fiber is a strong, lightweight material used in various high-performance applications, including bicycle manufacturing. name: Bicycle Manufacturing\ntype: Industry\ndescription: The bicycle manufacturing industry involves the production of bicycles for various uses, including racing and recreational cycling. name: Wooden Contraption\ntype: Historical Object\ndescription: An early form of the bicycle made from wood. name: steel\ntype: Material\ndescription: Steel is an alloy of iron and carbon, known for its strength and durability. It has been widely used in various applications, including bicycle frames. name: Safety Bicycle\ntype: Vehicle\ndescription: A bicycle with two wheels of equal size, a chain drive system, and pneumatic tires, making it more stable, comfortable, and efficient. name: Competitive Racing\ntype: Sport\ndescription: Competitive racing is a form of sport where participants compete in races, often on bicycles, showcasing speed, skill, and endurance. name: Carbon Fiber in Bicycle Construction\ntype: Material Innovation\ndescription: Carbon fiber was introduced as a revolutionary material, providing significant improvements in weight reduction and stiffness. name: Cruisers\ntype: Bicycle Type\ndescription: Comfortable bicycles designed for leisure and casual riding. name: Culture\ntype: Sector\ndescription: The arts, customs, and habits that characterize a particular society or nation. name: Bicycle\ntype: Vehicle\ndescription: A two-wheeled vehicle propelled by human power, with a rich history of evolution and innovation that spans centuries. name: Aluminum\ntype: Material\ndescription: Aluminum is a lightweight metal used in various applications, including bicycle frames. name: Cycling\ntype: Activity\ndescription: Cycling, the activity of riding bicycles, has evolved from a simple wooden contraption to a high-tech racing machine. It has had a profound impact on society, influencing transportation, recreation, and culture. name: Tour de France\ntype: Cycling Race\ndescription: The Tour de France is one of the most prestigious and challenging professional cycling races in the world, showcasing the speed, skill, and endurance of elite cyclists. name: Carbon Fiber\ntype: Material\ndescription: Carbon fiber is a composite material known for its lightweight, strength, and aerodynamic properties. name: Bicycle Frames\ntype: Product Component\ndescription: Bicycle frames are the structural components of bicycles that provide support and stability.",
    "evaluation": 1
  },
  {
    "correct_answer": "Carbon fiber frames are ideal for competitive racing and high-performance cycling.",
    "retrieved_context": "name: Elite Cyclists\ntype: Athlete\ndescription: Elite cyclists are highly skilled and physically fit athletes who compete at the highest levels of professional cycling. name: Racing Bikes\ntype: Bicycle Type\ndescription: High-performance bicycles designed for speed and competition. name: Transportation\ntype: Activity\ndescription: Using bicycles as a means of transportation for short and long distances. name: Late 20th Century\ntype: Time Period\ndescription: The late 20th century refers to the period from approximately 1970 to 1999. name: bicycle frames\ntype: Product Component\ndescription: Bicycle frames are the main structural components of bicycles, providing support and stability. name: High-performance cycling\ntype: Activity\ndescription: High-performance cycling involves the use of advanced materials and designs to achieve optimal speed, agility, and responsiveness in competitive racing. name: cruisers\ntype: Bicycle Style\ndescription: Cruisers are a type of bicycle designed for comfort and leisure, featuring upright seating positions and often wider tires. name: Recreation\ntype: Activity\ndescription: Engaging in leisure activities such as cycling for fun or exercise. name: Carbon Fiber Frames\ntype: Material\ndescription: Carbon fiber is a lightweight, strong, and aerodynamic material used in the construction of high-performance bicycles. name: carbon fiber\ntype: Material\ndescription: Carbon fiber is a strong, lightweight material used in various high-performance applications, including bicycle manufacturing. name: Bicycle Manufacturing\ntype: Industry\ndescription: The bicycle manufacturing industry involves the production of bicycles for various uses, including racing and recreational cycling. name: Aluminum and Titanium in Bicycle Construction\ntype: Material Innovation\ndescription: Aluminum and titanium emerged as popular alternatives to steel, providing lighter weight and increased stiffness for improved performance. name: Wooden Contraption\ntype: Historical Object\ndescription: An early form of the bicycle made from wood. name: Safety Bicycle\ntype: Vehicle\ndescription: A bicycle with two wheels of equal size, a chain drive system, and pneumatic tires, making it more stable, comfortable, and efficient. name: Competitive Racing\ntype: Sport\ndescription: Competitive racing is a form of sport where participants compete in races, often on bicycles, showcasing speed, skill, and endurance. name: Carbon Fiber in Bicycle Construction\ntype: Material Innovation\ndescription: Carbon fiber was introduced as a revolutionary material, providing significant improvements in weight reduction and stiffness. name: Cruisers\ntype: Bicycle Type\ndescription: Comfortable bicycles designed for leisure and casual riding. name: Culture\ntype: Sector\ndescription: The arts, customs, and habits that characterize a particular society or nation. name: Bicycle\ntype: Vehicle\ndescription: A two-wheeled vehicle propelled by human power, with a rich history of evolution and innovation that spans centuries. name: Cycling\ntype: Activity\ndescription: Cycling, the activity of riding bicycles, has evolved from a simple wooden contraption to a high-tech racing machine. It has had a profound impact on society, influencing transportation, recreation, and culture. name: Tour de France\ntype: Cycling Race\ndescription: The Tour de France is one of the most prestigious and challenging professional cycling races in the world, showcasing the speed, skill, and endurance of elite cyclists. name: Carbon Fiber\ntype: Material\ndescription: Carbon fiber is a composite material known for its lightweight, strength, and aerodynamic properties. name: Bicycle Frames\ntype: Product Component\ndescription: Bicycle frames are the structural components of bicycles that provide support and stability.",
    "evaluation": 1
  },
  {
    "correct_answer": "Electric bikes offer motorized assistance for easier riding and longer distances.",
    "retrieved_context": "name: Bicycle Innovations\ntype: Technological Advancements\ndescription: Innovations in bicycle design and technology have included improvements in materials, mechanics, and aerodynamics. name: Draisine\ntype: Vehicle\ndescription: A two-wheeled vehicle invented by Baron Karl von Drais in the early 19th century, propelled by the rider pushing off the ground with their feet. name: electric bikes\ntype: Bicycle Type\ndescription: Electric bikes are bicycles equipped with an electric motor to assist the rider, providing easier riding and longer distances. name: Racing Bikes\ntype: Bicycle Type\ndescription: High-performance bicycles designed for speed and competition. name: Transportation\ntype: Activity\ndescription: Using bicycles as a means of transportation for short and long distances. name: Recreation\ntype: Activity\ndescription: Engaging in leisure activities such as cycling for fun or exercise. name: Racing\ntype: Activity\ndescription: Competitive cycling events where participants race against each other. name: rear wheel\ntype: Bicycle Component\ndescription: The rear wheel of a bicycle is one of the two wheels that support and propel the vehicle. It can vary in size and design depending on the type of bicycle. name: bicycles\ntype: Transportation Mode\ndescription: Bicycles are two-wheeled vehicles used for transportation, exercise, and leisure. name: bicycle\ntype: Transportation Mode\ndescription: A bicycle is a human-powered or motor-assisted vehicle with two wheels, used for transportation and recreation. name: High-Wheel Bicycle (Penny-Farthing)\ntype: Bicycle Type\ndescription: The high-wheel bicycle, also known as the penny-farthing, was a significant milestone in the evolution of bicycles. It featured a large front wheel and a much smaller rear wheel. name: Front Wheel\ntype: Bicycle Component\ndescription: The front wheel of a bicycle, which can vary in size and design depending on the type of bicycle. name: Wooden Contraption\ntype: Historical Object\ndescription: An early form of the bicycle made from wood. name: Penny-Farthing\ntype: Vehicle\ndescription: A distinctive bicycle with a large front wheel and a smaller rear wheel, known for its speed and elegance but also dangerous due to its high center of gravity. name: Baron Karl von Drais\ntype: Person\ndescription: Baron Karl von Drais was a German inventor who created the draisine, an early version of the bicycle. name: Safety Bicycle\ntype: Vehicle\ndescription: A bicycle with two wheels of equal size, a chain drive system, and pneumatic tires, making it more stable, comfortable, and efficient. name: cyclists\ntype: Rider Group\ndescription: Cyclists are individuals who ride bicycles for various purposes such as commuting, exercise, and leisure. name: Cruisers\ntype: Bicycle Type\ndescription: Comfortable bicycles designed for leisure and casual riding. name: Culture\ntype: Sector\ndescription: The arts, customs, and habits that characterize a particular society or nation. name: Bicycle\ntype: Vehicle\ndescription: A two-wheeled vehicle propelled by human power, with a rich history of evolution and innovation that spans centuries. name: recent years\ntype: Time Period\ndescription: Recent years refer to the most recent period in time, typically within the last few decades. name: Velocipede (Boneshaker)\ntype: Vehicle\ndescription: An early bicycle with pedals attached directly to the front wheel, offering a smoother ride and greater speed than the draisine. name: Cycling\ntype: Activity\ndescription: Cycling, the activity of riding bicycles, has evolved from a simple wooden contraption to a high-tech racing machine. It has had a profound impact on society, influencing transportation, recreation, and culture. name: racing bikes\ntype: Bicycle Type\ndescription: Racing bikes are designed for speed and efficiency, often used in competitive cycling events. name: Tour de France\ntype: Cycling Race\ndescription: The Tour de France is one of the most prestigious and challenging professional cycling races in the world, showcasing the speed, skill, and endurance of elite cyclists. name: Penny-Farthing Bicycle\ntype: Bicycle Type\ndescription: A distinctive bicycle featuring a large front wheel and a smaller rear wheel, giving it a high center of gravity and a precarious ride. name: 19th century\ntype: Time Period\ndescription: The 19th century spans from the year 1801 to 1900. It was a period of significant technological and social change, including major advancements in transportation and communication. name: Commuting\ntype: Activity\ndescription: Traveling between home and work or school.",
    "evaluation": 1
  },
  {
    "correct_answer": "Bicycles have become a popular mode of transportation for commuting, exercise, and leisure.",
    "retrieved_context": "name: Bicycle Innovations\ntype: Technological Advancements\ndescription: Innovations in bicycle design and technology have included improvements in materials, mechanics, and aerodynamics. name: Draisine\ntype: Vehicle\ndescription: A two-wheeled vehicle invented by Baron Karl von Drais in the early 19th century, propelled by the rider pushing off the ground with their feet. name: Racing Bikes\ntype: Bicycle Type\ndescription: High-performance bicycles designed for speed and competition. name: Transportation\ntype: Activity\ndescription: Using bicycles as a means of transportation for short and long distances. name: High-performance cycling\ntype: Activity\ndescription: High-performance cycling involves the use of advanced materials and designs to achieve optimal speed, agility, and responsiveness in competitive racing. name: Recreation\ntype: Activity\ndescription: Engaging in leisure activities such as cycling for fun or exercise. name: Carbon Fiber Frames\ntype: Material\ndescription: Carbon fiber is a lightweight, strong, and aerodynamic material used in the construction of high-performance bicycles. name: Racing\ntype: Activity\ndescription: Competitive cycling events where participants race against each other. name: bicycles\ntype: Transportation Mode\ndescription: Bicycles are two-wheeled vehicles used for transportation, exercise, and leisure. name: bicycle\ntype: Transportation Mode\ndescription: A bicycle is a human-powered or motor-assisted vehicle with two wheels, used for transportation and recreation. name: public transportation\ntype: Transportation Mode\ndescription: Public transportation refers to shared passenger services that are available for use by the general public, such as buses, trains, and subways. name: Bicycle Evolution\ntype: Technological Development\ndescription: The evolution of the bicycle has been a continuous process, with advancements in materials, design, and technology throughout the 20th century. name: Wooden Contraption\ntype: Historical Object\ndescription: An early form of the bicycle made from wood. name: Penny-Farthing\ntype: Vehicle\ndescription: A distinctive bicycle with a large front wheel and a smaller rear wheel, known for its speed and elegance but also dangerous due to its high center of gravity. name: Safety Bicycle\ntype: Vehicle\ndescription: A bicycle with two wheels of equal size, a chain drive system, and pneumatic tires, making it more stable, comfortable, and efficient. name: Cruisers\ntype: Bicycle Type\ndescription: Comfortable bicycles designed for leisure and casual riding. name: Culture\ntype: Sector\ndescription: The arts, customs, and habits that characterize a particular society or nation. name: Bicycle\ntype: Vehicle\ndescription: A two-wheeled vehicle propelled by human power, with a rich history of evolution and innovation that spans centuries. name: Velocipede (Boneshaker)\ntype: Vehicle\ndescription: An early bicycle with pedals attached directly to the front wheel, offering a smoother ride and greater speed than the draisine. name: Cycling\ntype: Activity\ndescription: Cycling, the activity of riding bicycles, has evolved from a simple wooden contraption to a high-tech racing machine. It has had a profound impact on society, influencing transportation, recreation, and culture. name: Tour de France\ntype: Cycling Race\ndescription: The Tour de France is one of the most prestigious and challenging professional cycling races in the world, showcasing the speed, skill, and endurance of elite cyclists. name: Commuting\ntype: Activity\ndescription: Traveling between home and work or school.",
    "evaluation": 1
  },
  {
    "correct_answer": "Cycling has become a competitive sport enjoyed by millions of people around the world.",
    "retrieved_context": "name: Carbon Fiber Frames\ntype: Material\ndescription: Carbon fiber is a lightweight, strong, and aerodynamic material used in the construction of high-performance bicycles. name: Racing\ntype: Activity\ndescription: Competitive cycling events where participants race against each other. name: Wooden Contraption\ntype: Historical Object\ndescription: An early form of the bicycle made from wood. name: Elite Cyclists\ntype: Athlete\ndescription: Elite cyclists are highly skilled and physically fit athletes who compete at the highest levels of professional cycling. name: Cycling\ntype: Activity\ndescription: Cycling, the activity of riding bicycles, has evolved from a simple wooden contraption to a high-tech racing machine. It has had a profound impact on society, influencing transportation, recreation, and culture. name: Racing Bikes\ntype: Bicycle Type\ndescription: High-performance bicycles designed for speed and competition. name: Bicycle\ntype: Vehicle\ndescription: A two-wheeled vehicle propelled by human power, with a rich history of evolution and innovation that spans centuries. name: Tour de France\ntype: Cycling Race\ndescription: The Tour de France is one of the most prestigious and challenging professional cycling races in the world, showcasing the speed, skill, and endurance of elite cyclists. name: Safety Bicycle\ntype: Vehicle\ndescription: A bicycle with two wheels of equal size, a chain drive system, and pneumatic tires, making it more stable, comfortable, and efficient. name: Competitive Racing\ntype: Sport\ndescription: Competitive racing is a form of sport where participants compete in races, often on bicycles, showcasing speed, skill, and endurance. name: cyclists\ntype: Rider Group\ndescription: Cyclists are individuals who ride bicycles for various purposes such as commuting, exercise, and leisure. name: Transportation\ntype: Activity\ndescription: Using bicycles as a means of transportation for short and long distances. name: cruisers\ntype: Bicycle Style\ndescription: Cruisers are a type of bicycle designed for comfort and leisure, featuring upright seating positions and often wider tires. name: Cruisers\ntype: Bicycle Type\ndescription: Comfortable bicycles designed for leisure and casual riding. name: High-performance cycling\ntype: Activity\ndescription: High-performance cycling involves the use of advanced materials and designs to achieve optimal speed, agility, and responsiveness in competitive racing. name: Culture\ntype: Sector\ndescription: The arts, customs, and habits that characterize a particular society or nation. name: Recreation\ntype: Activity\ndescription: Engaging in leisure activities such as cycling for fun or exercise.",
    "evaluation": 1
  },
  {
    "accuracy": "93.33%"
  }
]