[
  {
    "correct_answer": "Color plays a crucial role in branding and marketing strategies.",
    "retrieved_context": "name: Trust and Reliability\ntype: Emotion\ndescription: A feeling of trust and reliability, often associated with stability and dependability. name: Brand Identity\ntype: Business Concept\ndescription: The unique set of characteristics that distinguish a brand from its competitors and create a strong presence in the market. name: Consumer Behavior\ntype: Concept\ndescription: Consumer behavior refers to the actions and decision-making processes of consumers in relation to purchasing and using goods and services. name: color psychology\ntype: Psychological Concept\ndescription: Color psychology is the study of how colors affect human behavior and perception. It is used by businesses to influence consumer perceptions. name: Competitors\ntype: Business Entities\ndescription: Competitors are other businesses that offer similar products or services in the same market. name: Marketing Strategies\ntype: Business Strategy\ndescription: Marketing strategies are comprehensive plans designed to achieve specific business objectives, such as increasing brand awareness, driving sales, and building customer loyalty. They often involve the use of color psychology to influence consumer behavior. name: green\ntype: Color\ndescription: Green is a color that evokes feelings of trust, reliability, and calmness. It can also create a sense of nature and growth. name: Perception of Value\ntype: Value Perception\ndescription: The perceived value associated with a product or service. name: Cultural and Contextual Associations\ntype: Concept\ndescription: Cultural and contextual associations refer to the meanings and perceptions of colors in different cultural and situational contexts. name: Colors\ntype: Visual Element\ndescription: Colors are visual elements that can evoke emotions and influence perceptions. They play a significant role in how consumers perceive a brand\"s personality, quality, and value. name: Nature and Growth\ntype: Concept\ndescription: The natural world, including plants, forests, and the environment. name: Brand Personality\ntype: Personality Trait\ndescription: The set of human characteristics attributed to a brand. name: Distinctive Color Scheme\ntype: Attribute\ndescription: A unique combination of colors that sets a brand apart from its competitors. name: Brand Perception\ntype: Concept\ndescription: The overall impression that consumers have about a brand. name: Color\ntype: Concept\ndescription: Color plays a crucial role in branding and marketing strategies, as it has the power to evoke emotions, convey messages, and influence consumer behavior. Different colors have different meanings and are often associated with particular emotions or qualities. name: brand identity\ntype: Concept\ndescription: Brand identity refers to the visual and emotional representation of a brand, including its name, logo, colors, and other elements that distinguish it from competitors. It is crucial for creating a strong connection with the target audience. name: Target Audience\ntype: Audience Segment\ndescription: The target audience refers to the specific group of people that a business aims to reach and engage with through its marketing efforts, products, or services. name: Brand Value\ntype: Perception\ndescription: The way consumers perceive a brand\"s value can be influenced by the colors used in branding. name: Calmness\ntype: Emotion\ndescription: A feeling of peace and tranquility, often associated with relaxation and serenity. name: Messages\ntype: Message\ndescription: Information or ideas communicated to an audience. name: Business\ntype: Organization\ndescription: A business is an organization that engages in commercial, industrial, or professional activities. name: Perception of Quality\ntype: Quality Perception\ndescription: The perceived level of quality associated with a product or service. name: orange\ntype: Color\ndescription: Orange is a warm color that can create a sense of urgency and encourage impulse purchases. It is often associated with warmth, energy, and excitement. name: Color Psychology\ntype: Concept\ndescription: The study of how colors influence human behavior and emotions. name: Emotions\ntype: Concept\ndescription: Emotions are complex psychological states that involve subjective feelings, physiological responses, and expressive behaviors. In the context of branding and marketing, emotions play a crucial role in influencing consumer behavior and perceptions. name: Yellow\ntype: Color\ndescription: Yellow is a bright and cheerful color often associated with happiness, optimism, and energy. name: Brand Quality\ntype: Concept\ndescription: Brand quality refers to the overall perception of the excellence or superiority of a brand\"s products or services.",
    "evaluation": 1
  },
  {
    "correct_answer": "Colors have the power to evoke emotions.",
    "retrieved_context": "name: Trust and Reliability\ntype: Emotion\ndescription: A feeling of trust and reliability, often associated with stability and dependability. name: Red\ntype: Color\ndescription: Red is a primary color that is often associated with passion, energy, and excitement. name: Brand Identity\ntype: Business Concept\ndescription: The unique set of characteristics that distinguish a brand from its competitors and create a strong presence in the market. name: Consumer Behavior\ntype: Concept\ndescription: Consumer behavior refers to the actions and decision-making processes of consumers in relation to purchasing and using goods and services. name: color psychology\ntype: Psychological Concept\ndescription: Color psychology is the study of how colors affect human behavior and perception. It is used by businesses to influence consumer perceptions. name: Competitors\ntype: Business Entities\ndescription: Competitors are other businesses that offer similar products or services in the same market. name: Marketing Strategies\ntype: Business Strategy\ndescription: Marketing strategies are comprehensive plans designed to achieve specific business objectives, such as increasing brand awareness, driving sales, and building customer loyalty. They often involve the use of color psychology to influence consumer behavior. name: green\ntype: Color\ndescription: Green is a color that evokes feelings of trust, reliability, and calmness. It can also create a sense of nature and growth. name: Perception of Value\ntype: Value Perception\ndescription: The perceived value associated with a product or service. name: Blue\ntype: Color\ndescription: Blue is a primary color that is often associated with trust, reliability, and calmness. name: Cultural and Contextual Associations\ntype: Concept\ndescription: Cultural and contextual associations refer to the meanings and perceptions of colors in different cultural and situational contexts. name: Color Meanings and Associations\ntype: Concept\ndescription: The meanings and associations of colors can vary significantly across different cultures. name: Nature and Growth\ntype: Concept\ndescription: The natural world, including plants, forests, and the environment. name: Colors\ntype: Visual Element\ndescription: Colors are visual elements that can evoke emotions and influence perceptions. They play a significant role in how consumers perceive a brand\"s personality, quality, and value. name: Brand Personality\ntype: Personality Trait\ndescription: The set of human characteristics attributed to a brand. name: Brand Perception\ntype: Concept\ndescription: The overall impression that consumers have about a brand. name: brand identity\ntype: Concept\ndescription: Brand identity refers to the visual and emotional representation of a brand, including its name, logo, colors, and other elements that distinguish it from competitors. It is crucial for creating a strong connection with the target audience. name: Color\ntype: Concept\ndescription: Color plays a crucial role in branding and marketing strategies, as it has the power to evoke emotions, convey messages, and influence consumer behavior. Different colors have different meanings and are often associated with particular emotions or qualities. name: Target Audience\ntype: Audience Segment\ndescription: The target audience refers to the specific group of people that a business aims to reach and engage with through its marketing efforts, products, or services. name: Calmness\ntype: Emotion\ndescription: A feeling of peace and tranquility, often associated with relaxation and serenity. name: Messages\ntype: Message\ndescription: Information or ideas communicated to an audience. name: Business\ntype: Organization\ndescription: A business is an organization that engages in commercial, industrial, or professional activities. name: Perception of Quality\ntype: Quality Perception\ndescription: The perceived level of quality associated with a product or service. name: Color Psychology\ntype: Concept\ndescription: The study of how colors influence human behavior and emotions. name: Emotions\ntype: Concept\ndescription: Emotions are complex psychological states that involve subjective feelings, physiological responses, and expressive behaviors. In the context of branding and marketing, emotions play a crucial role in influencing consumer behavior and perceptions. name: Yellow\ntype: Color\ndescription: Yellow is a bright and cheerful color often associated with happiness, optimism, and energy.",
    "evaluation": 1
  },
  {
    "correct_answer": "Colors can convey messages.",
    "retrieved_context": "name: Trust and Reliability\ntype: Emotion\ndescription: A feeling of trust and reliability, often associated with stability and dependability. name: Brand Identity\ntype: Business Concept\ndescription: The unique set of characteristics that distinguish a brand from its competitors and create a strong presence in the market. name: Consumer Behavior\ntype: Concept\ndescription: Consumer behavior refers to the actions and decision-making processes of consumers in relation to purchasing and using goods and services. name: color psychology\ntype: Psychological Concept\ndescription: Color psychology is the study of how colors affect human behavior and perception. It is used by businesses to influence consumer perceptions. name: Competitors\ntype: Business Entities\ndescription: Competitors are other businesses that offer similar products or services in the same market. name: Marketing Strategies\ntype: Business Strategy\ndescription: Marketing strategies are comprehensive plans designed to achieve specific business objectives, such as increasing brand awareness, driving sales, and building customer loyalty. They often involve the use of color psychology to influence consumer behavior. name: green\ntype: Color\ndescription: Green is a color that evokes feelings of trust, reliability, and calmness. It can also create a sense of nature and growth. name: Perception of Value\ntype: Value Perception\ndescription: The perceived value associated with a product or service. name: Cultural and Contextual Associations\ntype: Concept\ndescription: Cultural and contextual associations refer to the meanings and perceptions of colors in different cultural and situational contexts. name: Color Meanings and Associations\ntype: Concept\ndescription: The meanings and associations of colors can vary significantly across different cultures. name: Nature and Growth\ntype: Concept\ndescription: The natural world, including plants, forests, and the environment. name: Colors\ntype: Visual Element\ndescription: Colors are visual elements that can evoke emotions and influence perceptions. They play a significant role in how consumers perceive a brand\"s personality, quality, and value. name: Brand Personality\ntype: Personality Trait\ndescription: The set of human characteristics attributed to a brand. name: Distinctive Color Scheme\ntype: Attribute\ndescription: A unique combination of colors that sets a brand apart from its competitors. name: Brand Perception\ntype: Concept\ndescription: The overall impression that consumers have about a brand. name: Color\ntype: Concept\ndescription: Color plays a crucial role in branding and marketing strategies, as it has the power to evoke emotions, convey messages, and influence consumer behavior. Different colors have different meanings and are often associated with particular emotions or qualities. name: brand identity\ntype: Concept\ndescription: Brand identity refers to the visual and emotional representation of a brand, including its name, logo, colors, and other elements that distinguish it from competitors. It is crucial for creating a strong connection with the target audience. name: Target Audience\ntype: Audience Segment\ndescription: The target audience refers to the specific group of people that a business aims to reach and engage with through its marketing efforts, products, or services. name: Calmness\ntype: Emotion\ndescription: A feeling of peace and tranquility, often associated with relaxation and serenity. name: Messages\ntype: Message\ndescription: Information or ideas communicated to an audience. name: Business\ntype: Organization\ndescription: A business is an organization that engages in commercial, industrial, or professional activities. name: Perception of Quality\ntype: Quality Perception\ndescription: The perceived level of quality associated with a product or service. name: Color Psychology\ntype: Concept\ndescription: The study of how colors influence human behavior and emotions. name: Emotions\ntype: Concept\ndescription: Emotions are complex psychological states that involve subjective feelings, physiological responses, and expressive behaviors. In the context of branding and marketing, emotions play a crucial role in influencing consumer behavior and perceptions. name: Yellow\ntype: Color\ndescription: Yellow is a bright and cheerful color often associated with happiness, optimism, and energy.",
    "evaluation": 1
  },
  {
    "correct_answer": "Colors influence consumer behavior.",
    "retrieved_context": "name: Brand Identity\ntype: Business Concept\ndescription: The unique set of characteristics that distinguish a brand from its competitors and create a strong presence in the market. name: Consumer Behavior\ntype: Concept\ndescription: Consumer behavior refers to the actions and decision-making processes of consumers in relation to purchasing and using goods and services. name: color psychology\ntype: Psychological Concept\ndescription: Color psychology is the study of how colors affect human behavior and perception. It is used by businesses to influence consumer perceptions. name: Competitors\ntype: Business Entities\ndescription: Competitors are other businesses that offer similar products or services in the same market. name: Marketing Strategies\ntype: Business Strategy\ndescription: Marketing strategies are comprehensive plans designed to achieve specific business objectives, such as increasing brand awareness, driving sales, and building customer loyalty. They often involve the use of color psychology to influence consumer behavior. name: Perception of Value\ntype: Value Perception\ndescription: The perceived value associated with a product or service. name: Cultural and Contextual Associations\ntype: Concept\ndescription: Cultural and contextual associations refer to the meanings and perceptions of colors in different cultural and situational contexts. name: Color Meanings and Associations\ntype: Concept\ndescription: The meanings and associations of colors can vary significantly across different cultures. name: Brand Personality\ntype: Personality Trait\ndescription: The set of human characteristics attributed to a brand. name: Brand Perception\ntype: Concept\ndescription: The overall impression that consumers have about a brand. name: Distinctive Color Scheme\ntype: Attribute\ndescription: A unique combination of colors that sets a brand apart from its competitors. name: Color\ntype: Concept\ndescription: Color plays a crucial role in branding and marketing strategies, as it has the power to evoke emotions, convey messages, and influence consumer behavior. Different colors have different meanings and are often associated with particular emotions or qualities. name: brand identity\ntype: Concept\ndescription: Brand identity refers to the visual and emotional representation of a brand, including its name, logo, colors, and other elements that distinguish it from competitors. It is crucial for creating a strong connection with the target audience. name: Target Audience\ntype: Audience Segment\ndescription: The target audience refers to the specific group of people that a business aims to reach and engage with through its marketing efforts, products, or services. name: Consumer Perception\ntype: Concept\ndescription: Consumer perception refers to the way consumers interpret and form opinions about a brand based on various factors, including visual elements like color. name: Messages\ntype: Message\ndescription: Information or ideas communicated to an audience. name: Business\ntype: Organization\ndescription: A business is an organization that engages in commercial, industrial, or professional activities. name: Perception of Quality\ntype: Quality Perception\ndescription: The perceived level of quality associated with a product or service. name: Color Psychology\ntype: Concept\ndescription: The study of how colors influence human behavior and emotions. name: Emotions\ntype: Concept\ndescription: Emotions are complex psychological states that involve subjective feelings, physiological responses, and expressive behaviors. In the context of branding and marketing, emotions play a crucial role in influencing consumer behavior and perceptions. name: Emotional Connection\ntype: Consumer Psychology\ndescription: Emotional connection refers to the emotional bond that consumers form with a brand, often influenced by color and design elements.",
    "evaluation": 1
  },
  {
    "correct_answer": "Understanding color psychology helps create a strong brand identity.",
    "retrieved_context": "name: Contextual Factors\ntype: Factor\ndescription: Elements that are influenced by the specific context in which a brand is presented, such as industry norms and market conditions. name: Brand Identity\ntype: Business Concept\ndescription: The unique set of characteristics that distinguish a brand from its competitors and create a strong presence in the market. name: Consumer Behavior\ntype: Concept\ndescription: Consumer behavior refers to the actions and decision-making processes of consumers in relation to purchasing and using goods and services. name: color psychology\ntype: Psychological Concept\ndescription: Color psychology is the study of how colors affect human behavior and perception. It is used by businesses to influence consumer perceptions. name: Competitors\ntype: Business Entities\ndescription: Competitors are other businesses that offer similar products or services in the same market. name: Marketing Strategies\ntype: Business Strategy\ndescription: Marketing strategies are comprehensive plans designed to achieve specific business objectives, such as increasing brand awareness, driving sales, and building customer loyalty. They often involve the use of color psychology to influence consumer behavior. name: Perception of Value\ntype: Value Perception\ndescription: The perceived value associated with a product or service. name: Cultural and Contextual Associations\ntype: Concept\ndescription: Cultural and contextual associations refer to the meanings and perceptions of colors in different cultural and situational contexts. name: Brand Presence\ntype: Outcome\ndescription: The overall visibility and recognition of a brand among consumers. name: Branding\ntype: Concept\ndescription: Branding refers to the practice of creating a name, symbol, or design that identifies and differentiates a product, service, or organization from its competitors. name: Brand Personality\ntype: Personality Trait\ndescription: The set of human characteristics attributed to a brand. name: brand identity\ntype: Concept\ndescription: Brand identity refers to the visual and emotional representation of a brand, including its name, logo, colors, and other elements that distinguish it from competitors. It is crucial for creating a strong connection with the target audience. name: Strong Brand Identity\ntype: Concept\ndescription: A strong brand identity is a consistent and distinctive set of characteristics that make a brand recognizable and memorable. name: Distinctive Color Scheme\ntype: Attribute\ndescription: A unique combination of colors that sets a brand apart from its competitors. name: Color\ntype: Concept\ndescription: Color plays a crucial role in branding and marketing strategies, as it has the power to evoke emotions, convey messages, and influence consumer behavior. Different colors have different meanings and are often associated with particular emotions or qualities. name: Brand Perception\ntype: Concept\ndescription: The overall impression that consumers have about a brand. name: Target Audience\ntype: Audience Segment\ndescription: The target audience refers to the specific group of people that a business aims to reach and engage with through its marketing efforts, products, or services. name: Messages\ntype: Message\ndescription: Information or ideas communicated to an audience. name: Business\ntype: Organization\ndescription: A business is an organization that engages in commercial, industrial, or professional activities. name: Perception of Quality\ntype: Quality Perception\ndescription: The perceived level of quality associated with a product or service. name: Color Psychology\ntype: Concept\ndescription: The study of how colors influence human behavior and emotions. name: Cultural Factors\ntype: Factor\ndescription: Elements that are influenced by the cultural background of a target audience, such as traditions, values, and beliefs. name: Emotions\ntype: Concept\ndescription: Emotions are complex psychological states that involve subjective feelings, physiological responses, and expressive behaviors. In the context of branding and marketing, emotions play a crucial role in influencing consumer behavior and perceptions.",
    "evaluation": 1
  },
  {
    "correct_answer": "Different colors evoke specific emotions and associations.",
    "retrieved_context": "name: Trust and Reliability\ntype: Emotion\ndescription: A feeling of trust and reliability, often associated with stability and dependability. name: Brand Identity\ntype: Business Concept\ndescription: The unique set of characteristics that distinguish a brand from its competitors and create a strong presence in the market. name: Consumer Behavior\ntype: Concept\ndescription: Consumer behavior refers to the actions and decision-making processes of consumers in relation to purchasing and using goods and services. name: color psychology\ntype: Psychological Concept\ndescription: Color psychology is the study of how colors affect human behavior and perception. It is used by businesses to influence consumer perceptions. name: Competitors\ntype: Business Entities\ndescription: Competitors are other businesses that offer similar products or services in the same market. name: Marketing Strategies\ntype: Business Strategy\ndescription: Marketing strategies are comprehensive plans designed to achieve specific business objectives, such as increasing brand awareness, driving sales, and building customer loyalty. They often involve the use of color psychology to influence consumer behavior. name: green\ntype: Color\ndescription: Green is a color that evokes feelings of trust, reliability, and calmness. It can also create a sense of nature and growth. name: Perception of Value\ntype: Value Perception\ndescription: The perceived value associated with a product or service. name: Cultural and Contextual Associations\ntype: Concept\ndescription: Cultural and contextual associations refer to the meanings and perceptions of colors in different cultural and situational contexts. name: Color Meanings and Associations\ntype: Concept\ndescription: The meanings and associations of colors can vary significantly across different cultures. name: Nature and Growth\ntype: Concept\ndescription: The natural world, including plants, forests, and the environment. name: Brand Personality\ntype: Personality Trait\ndescription: The set of human characteristics attributed to a brand. name: Distinctive Color Scheme\ntype: Attribute\ndescription: A unique combination of colors that sets a brand apart from its competitors. name: Brand Perception\ntype: Concept\ndescription: The overall impression that consumers have about a brand. name: Color\ntype: Concept\ndescription: Color plays a crucial role in branding and marketing strategies, as it has the power to evoke emotions, convey messages, and influence consumer behavior. Different colors have different meanings and are often associated with particular emotions or qualities. name: brand identity\ntype: Concept\ndescription: Brand identity refers to the visual and emotional representation of a brand, including its name, logo, colors, and other elements that distinguish it from competitors. It is crucial for creating a strong connection with the target audience. name: Target Audience\ntype: Audience Segment\ndescription: The target audience refers to the specific group of people that a business aims to reach and engage with through its marketing efforts, products, or services. name: Brand Value\ntype: Perception\ndescription: The way consumers perceive a brand\"s value can be influenced by the colors used in branding. name: Calmness\ntype: Emotion\ndescription: A feeling of peace and tranquility, often associated with relaxation and serenity. name: Messages\ntype: Message\ndescription: Information or ideas communicated to an audience. name: Business\ntype: Organization\ndescription: A business is an organization that engages in commercial, industrial, or professional activities. name: Perception of Quality\ntype: Quality Perception\ndescription: The perceived level of quality associated with a product or service. name: orange\ntype: Color\ndescription: Orange is a warm color that can create a sense of urgency and encourage impulse purchases. It is often associated with warmth, energy, and excitement. name: Color Psychology\ntype: Concept\ndescription: The study of how colors influence human behavior and emotions. name: Emotions\ntype: Concept\ndescription: Emotions are complex psychological states that involve subjective feelings, physiological responses, and expressive behaviors. In the context of branding and marketing, emotions play a crucial role in influencing consumer behavior and perceptions. name: Yellow\ntype: Color\ndescription: Yellow is a bright and cheerful color often associated with happiness, optimism, and energy. name: Brand Quality\ntype: Concept\ndescription: Brand quality refers to the overall perception of the excellence or superiority of a brand\"s products or services.",
    "evaluation": 1
  },
  {
    "correct_answer": "Red is associated with passion, energy, and excitement.",
    "retrieved_context": "name: Brand Quality\ntype: Concept\ndescription: Brand quality refers to the overall perception of the excellence or superiority of a brand\"s products or services. name: Trust and Reliability\ntype: Emotion\ndescription: A feeling of trust and reliability, often associated with stability and dependability. name: Red\ntype: Color\ndescription: Red is a primary color that is often associated with passion, energy, and excitement. name: Calmness\ntype: Emotion\ndescription: A feeling of peace and tranquility, often associated with relaxation and serenity. name: Distinctive Color Scheme\ntype: Attribute\ndescription: A unique combination of colors that sets a brand apart from its competitors. name: Blue\ntype: Color\ndescription: Blue is a primary color that is often associated with trust, reliability, and calmness. name: Brand Perception\ntype: Concept\ndescription: The overall impression that consumers have about a brand. name: orange\ntype: Color\ndescription: Orange is a warm color that can create a sense of urgency and encourage impulse purchases. It is often associated with warmth, energy, and excitement. name: Business Decisions\ntype: Concept\ndescription: Businesses must consider cultural factors when making decisions about branding, especially regarding color choices. name: Color Psychology\ntype: Concept\ndescription: The study of how colors influence human behavior and emotions. name: green\ntype: Color\ndescription: Green is a color that evokes feelings of trust, reliability, and calmness. It can also create a sense of nature and growth. name: Cultures\ntype: Concept\ndescription: Cultures are the customs, arts, social institutions, and achievements of a particular nation, people, or other social group. name: Yellow\ntype: Color\ndescription: Yellow is a bright and cheerful color often associated with happiness, optimism, and energy. name: Color Meanings and Associations\ntype: Concept\ndescription: The meanings and associations of colors can vary significantly across different cultures. name: Brand Value\ntype: Perception\ndescription: The way consumers perceive a brand\"s value can be influenced by the colors used in branding. name: Nature and Growth\ntype: Concept\ndescription: The natural world, including plants, forests, and the environment. name: Brand Personality\ntype: Personality Trait\ndescription: The set of human characteristics attributed to a brand.",
    "evaluation": 1
  },
  {
    "correct_answer": "Blue is associated with trust, reliability, and calmness.",
    "retrieved_context": "name: Brand Quality\ntype: Concept\ndescription: Brand quality refers to the overall perception of the excellence or superiority of a brand\"s products or services. name: white\ntype: Color\ndescription: White is a color that can have different meanings and effects depending on the cultural context. In Western cultures, it is associated with purity and cleanliness, while in Eastern cultures, it is often associated with mourning and death. name: Trust and Reliability\ntype: Emotion\ndescription: A feeling of trust and reliability, often associated with stability and dependability. name: Nature and Growth\ntype: Concept\ndescription: The natural world, including plants, forests, and the environment. name: Brand Personality\ntype: Personality Trait\ndescription: The set of human characteristics attributed to a brand. name: Blue\ntype: Color\ndescription: Blue is a primary color that is often associated with trust, reliability, and calmness. name: Western Cultures\ntype: Culture\ndescription: Western cultures include countries and regions primarily influenced by European traditions and values. name: orange\ntype: Color\ndescription: Orange is a warm color that can create a sense of urgency and encourage impulse purchases. It is often associated with warmth, energy, and excitement. name: Eastern Cultures\ntype: Culture\ndescription: Eastern cultures include countries and regions primarily influenced by Asian traditions and values. name: color psychology\ntype: Psychological Concept\ndescription: Color psychology is the study of how colors affect human behavior and perception. It is used by businesses to influence consumer perceptions. name: Color Meanings and Associations\ntype: Concept\ndescription: The meanings and associations of colors can vary significantly across different cultures. name: Brand Value\ntype: Perception\ndescription: The way consumers perceive a brand\"s value can be influenced by the colors used in branding. name: Calmness\ntype: Emotion\ndescription: A feeling of peace and tranquility, often associated with relaxation and serenity. name: green\ntype: Color\ndescription: Green is a color that evokes feelings of trust, reliability, and calmness. It can also create a sense of nature and growth.",
    "evaluation": 1
  },
  {
    "correct_answer": "Colors affect how consumers perceive a brand's personality, quality, and value.",
    "retrieved_context": "name: Brand Quality\ntype: Concept\ndescription: Brand quality refers to the overall perception of the excellence or superiority of a brand\"s products or services. name: Strong Brand Identity\ntype: Concept\ndescription: A strong brand identity is a consistent and distinctive set of characteristics that make a brand recognizable and memorable. name: Brand Perception\ntype: Concept\ndescription: The overall impression that consumers have about a brand. name: brand\"s personality\ntype: Concept\ndescription: Brand\"s personality refers to the set of human characteristics associated with a brand, which can influence consumer perceptions and behaviors. name: Perception of Quality\ntype: Quality Perception\ndescription: The perceived level of quality associated with a product or service. name: Cultural and Contextual Factors\ntype: Concept\ndescription: Cultural and contextual factors include societal norms, values, and environmental influences that can affect consumer behavior. name: orange\ntype: Color\ndescription: Orange is a warm color that can create a sense of urgency and encourage impulse purchases. It is often associated with warmth, energy, and excitement. name: value\ntype: Concept\ndescription: Value, in the context of branding and consumer perception, refers to the perceived worth or importance that consumers attribute to a brand. It can be influenced by various factors including color psychology. name: Color Psychology\ntype: Concept\ndescription: The study of how colors influence human behavior and emotions. name: Consumer Perceptions\ntype: Concept\ndescription: Consumer perceptions are the subjective interpretations and evaluations that consumers have about a brand. name: Consumer Perception\ntype: Concept\ndescription: Consumer perception refers to the way consumers interpret and form opinions about a brand based on various factors, including visual elements like color. name: color psychology\ntype: Psychological Concept\ndescription: Color psychology is the study of how colors affect human behavior and perception. It is used by businesses to influence consumer perceptions. name: Brand Value\ntype: Perception\ndescription: The way consumers perceive a brand\"s value can be influenced by the colors used in branding. name: Brand Personality\ntype: Personality Trait\ndescription: The set of human characteristics attributed to a brand.",
    "evaluation": 1
  },
  {
    "correct_answer": "Warm colors like red and orange create a sense of urgency.",
    "retrieved_context": "name: Trust and Reliability\ntype: Emotion\ndescription: A feeling of trust and reliability, often associated with stability and dependability. name: Red\ntype: Color\ndescription: Red is a primary color that is often associated with passion, energy, and excitement. name: white\ntype: Color\ndescription: White is a color that can have different meanings and effects depending on the cultural context. In Western cultures, it is associated with purity and cleanliness, while in Eastern cultures, it is often associated with mourning and death. name: Consumers\ntype: Consumer Group\ndescription: Consumers are individuals who purchase and use Coca-Cola products. name: Brand Identity\ntype: Business Concept\ndescription: The unique set of characteristics that distinguish a brand from its competitors and create a strong presence in the market. name: Western Cultures\ntype: Culture\ndescription: Western cultures include countries and regions primarily influenced by European traditions and values. name: Coca-Cola\ntype: Brand\ndescription: Coca-Cola is a globally recognized soft drink brand known for its iconic red logo and distinctive taste. name: green\ntype: Color\ndescription: Green is a color that evokes feelings of trust, reliability, and calmness. It can also create a sense of nature and growth. name: Blue\ntype: Color\ndescription: Blue is a primary color that is often associated with trust, reliability, and calmness. name: Competitor Brands\ntype: Brand\ndescription: Competitor brands are other soft drink companies that compete with Coca-Cola in the market. name: Nature and Growth\ntype: Concept\ndescription: The natural world, including plants, forests, and the environment. name: Brand Personality\ntype: Personality Trait\ndescription: The set of human characteristics attributed to a brand. name: Distinctive Color Scheme\ntype: Attribute\ndescription: A unique combination of colors that sets a brand apart from its competitors. name: Brand Value\ntype: Perception\ndescription: The way consumers perceive a brand\"s value can be influenced by the colors used in branding. name: Calmness\ntype: Emotion\ndescription: A feeling of peace and tranquility, often associated with relaxation and serenity. name: orange\ntype: Color\ndescription: Orange is a warm color that can create a sense of urgency and encourage impulse purchases. It is often associated with warmth, energy, and excitement. name: Eastern Cultures\ntype: Culture\ndescription: Eastern cultures include countries and regions primarily influenced by Asian traditions and values. name: Color Psychology\ntype: Concept\ndescription: The study of how colors influence human behavior and emotions. name: McDonald\"s\ntype: Brand\ndescription: McDonald\"s is a global fast-food restaurant chain known for its iconic bright yellow arches and recognizable brand identity. name: Yellow\ntype: Color\ndescription: Yellow is a bright and cheerful color often associated with happiness, optimism, and energy. name: Brand Quality\ntype: Concept\ndescription: Brand quality refers to the overall perception of the excellence or superiority of a brand\"s products or services.",
    "evaluation": 1
  },
  {
    "correct_answer": "Cool colors like blue and green create a sense of trust.",
    "retrieved_context": "name: Trust and Reliability\ntype: Emotion\ndescription: A feeling of trust and reliability, often associated with stability and dependability. name: Consumer Behavior\ntype: Concept\ndescription: Consumer behavior refers to the actions and decision-making processes of consumers in relation to purchasing and using goods and services. name: color psychology\ntype: Psychological Concept\ndescription: Color psychology is the study of how colors affect human behavior and perception. It is used by businesses to influence consumer perceptions. name: green\ntype: Color\ndescription: Green is a color that evokes feelings of trust, reliability, and calmness. It can also create a sense of nature and growth. name: Perception of Value\ntype: Value Perception\ndescription: The perceived value associated with a product or service. name: Blue\ntype: Color\ndescription: Blue is a primary color that is often associated with trust, reliability, and calmness. name: Color Meanings and Associations\ntype: Concept\ndescription: The meanings and associations of colors can vary significantly across different cultures. name: Nature and Growth\ntype: Concept\ndescription: The natural world, including plants, forests, and the environment. name: Brand Personality\ntype: Personality Trait\ndescription: The set of human characteristics attributed to a brand. name: Color\ntype: Concept\ndescription: Color plays a crucial role in branding and marketing strategies, as it has the power to evoke emotions, convey messages, and influence consumer behavior. Different colors have different meanings and are often associated with particular emotions or qualities. name: Brand Value\ntype: Perception\ndescription: The way consumers perceive a brand\"s value can be influenced by the colors used in branding. name: Calmness\ntype: Emotion\ndescription: A feeling of peace and tranquility, often associated with relaxation and serenity. name: Messages\ntype: Message\ndescription: Information or ideas communicated to an audience. name: Perception of Quality\ntype: Quality Perception\ndescription: The perceived level of quality associated with a product or service. name: orange\ntype: Color\ndescription: Orange is a warm color that can create a sense of urgency and encourage impulse purchases. It is often associated with warmth, energy, and excitement. name: Color Psychology\ntype: Concept\ndescription: The study of how colors influence human behavior and emotions. name: Emotions\ntype: Concept\ndescription: Emotions are complex psychological states that involve subjective feelings, physiological responses, and expressive behaviors. In the context of branding and marketing, emotions play a crucial role in influencing consumer behavior and perceptions. name: Yellow\ntype: Color\ndescription: Yellow is a bright and cheerful color often associated with happiness, optimism, and energy. name: Brand Quality\ntype: Concept\ndescription: Brand quality refers to the overall perception of the excellence or superiority of a brand\"s products or services.",
    "evaluation": 1
  },
  {
    "correct_answer": "Colors help differentiate a brand from competitors.",
    "retrieved_context": "name: Contextual Factors\ntype: Factor\ndescription: Elements that are influenced by the specific context in which a brand is presented, such as industry norms and market conditions. name: Brand Identity\ntype: Business Concept\ndescription: The unique set of characteristics that distinguish a brand from its competitors and create a strong presence in the market. name: Competitors\ntype: Business Entities\ndescription: Competitors are other businesses that offer similar products or services in the same market. name: Memorable Brand\ntype: Concept\ndescription: A brand that is easily remembered by consumers. name: brand differentiation\ntype: Business Strategy\ndescription: Brand differentiation refers to the process of distinguishing a brand from its competitors in the marketplace, often through unique attributes such as color schemes, logos, and emotional connections with consumers. name: Cultural and Contextual Associations\ntype: Concept\ndescription: Cultural and contextual associations refer to the meanings and perceptions of colors in different cultural and situational contexts. name: businesses\ntype: Organization\ndescription: Businesses are organizations that engage in commercial, industrial, or professional activities. They can leverage the power of color psychology to create a successful and memorable brand. name: Brand Presence\ntype: Outcome\ndescription: The overall visibility and recognition of a brand among consumers. name: Competitor Brands\ntype: Brand\ndescription: Competitor brands are other soft drink companies that compete with Coca-Cola in the market. name: Branding\ntype: Concept\ndescription: Branding refers to the practice of creating a name, symbol, or design that identifies and differentiates a product, service, or organization from its competitors. name: Distinctive Color Scheme\ntype: Attribute\ndescription: A unique combination of colors that sets a brand apart from its competitors. name: Brand Perception\ntype: Concept\ndescription: The overall impression that consumers have about a brand. name: brand identity\ntype: Concept\ndescription: Brand identity refers to the visual and emotional representation of a brand, including its name, logo, colors, and other elements that distinguish it from competitors. It is crucial for creating a strong connection with the target audience. name: Strong Brand Identity\ntype: Concept\ndescription: A strong brand identity is a consistent and distinctive set of characteristics that make a brand recognizable and memorable. name: Target Audience\ntype: Audience Segment\ndescription: The target audience refers to the specific group of people that a business aims to reach and engage with through its marketing efforts, products, or services. name: Consumer Recognition\ntype: Marketing Outcome\ndescription: Consumer recognition refers to the ability of consumers to identify and recall a brand, often through distinctive visual elements. name: Brand Differentiation\ntype: Concept\ndescription: The process of distinguishing a brand from its competitors in the market. name: Color Psychology\ntype: Concept\ndescription: The study of how colors influence human behavior and emotions. name: Cultural Factors\ntype: Factor\ndescription: Elements that are influenced by the cultural background of a target audience, such as traditions, values, and beliefs. name: Emotional Connection\ntype: Consumer Psychology\ndescription: Emotional connection refers to the emotional bond that consumers form with a brand, often influenced by color and design elements. name: Market Presence\ntype: Business Outcome\ndescription: Market presence refers to the visibility and impact of a brand in its target market.",
    "evaluation": 1
  },
  {
    "correct_answer": "Cultural associations of colors should be considered in branding.",
    "retrieved_context": "name: Contextual Factors\ntype: Factor\ndescription: Elements that are influenced by the specific context in which a brand is presented, such as industry norms and market conditions. name: Brand Identity\ntype: Business Concept\ndescription: The unique set of characteristics that distinguish a brand from its competitors and create a strong presence in the market. name: Consumer Behavior\ntype: Concept\ndescription: Consumer behavior refers to the actions and decision-making processes of consumers in relation to purchasing and using goods and services. name: Competitors\ntype: Business Entities\ndescription: Competitors are other businesses that offer similar products or services in the same market. name: Memorable Brand\ntype: Concept\ndescription: A brand that is easily remembered by consumers. name: Perception of Value\ntype: Value Perception\ndescription: The perceived value associated with a product or service. name: Cultural and Contextual Associations\ntype: Concept\ndescription: Cultural and contextual associations refer to the meanings and perceptions of colors in different cultural and situational contexts. name: businesses\ntype: Organization\ndescription: Businesses are organizations that engage in commercial, industrial, or professional activities. They can leverage the power of color psychology to create a successful and memorable brand. name: Color Meanings and Associations\ntype: Concept\ndescription: The meanings and associations of colors can vary significantly across different cultures. name: Brand Presence\ntype: Outcome\ndescription: The overall visibility and recognition of a brand among consumers. name: Brand Personality\ntype: Personality Trait\ndescription: The set of human characteristics attributed to a brand. name: Branding\ntype: Concept\ndescription: Branding refers to the practice of creating a name, symbol, or design that identifies and differentiates a product, service, or organization from its competitors. name: Distinctive Color Scheme\ntype: Attribute\ndescription: A unique combination of colors that sets a brand apart from its competitors. name: Strong Brand Identity\ntype: Concept\ndescription: A strong brand identity is a consistent and distinctive set of characteristics that make a brand recognizable and memorable. name: Color\ntype: Concept\ndescription: Color plays a crucial role in branding and marketing strategies, as it has the power to evoke emotions, convey messages, and influence consumer behavior. Different colors have different meanings and are often associated with particular emotions or qualities. name: brand identity\ntype: Concept\ndescription: Brand identity refers to the visual and emotional representation of a brand, including its name, logo, colors, and other elements that distinguish it from competitors. It is crucial for creating a strong connection with the target audience. name: Brand Perception\ntype: Concept\ndescription: The overall impression that consumers have about a brand. name: Target Audience\ntype: Audience Segment\ndescription: The target audience refers to the specific group of people that a business aims to reach and engage with through its marketing efforts, products, or services. name: Messages\ntype: Message\ndescription: Information or ideas communicated to an audience. name: Brand Differentiation\ntype: Concept\ndescription: The process of distinguishing a brand from its competitors in the market. name: Perception of Quality\ntype: Quality Perception\ndescription: The perceived level of quality associated with a product or service. name: Color Psychology\ntype: Concept\ndescription: The study of how colors influence human behavior and emotions. name: Cultural Factors\ntype: Factor\ndescription: Elements that are influenced by the cultural background of a target audience, such as traditions, values, and beliefs. name: Emotions\ntype: Concept\ndescription: Emotions are complex psychological states that involve subjective feelings, physiological responses, and expressive behaviors. In the context of branding and marketing, emotions play a crucial role in influencing consumer behavior and perceptions.",
    "evaluation": 1
  },
  {
    "correct_answer": "Context influences the meaning and effects of colors in branding.",
    "retrieved_context": "name: Trust and Reliability\ntype: Emotion\ndescription: A feeling of trust and reliability, often associated with stability and dependability. name: Contextual Factors\ntype: Factor\ndescription: Elements that are influenced by the specific context in which a brand is presented, such as industry norms and market conditions. name: Brand Identity\ntype: Business Concept\ndescription: The unique set of characteristics that distinguish a brand from its competitors and create a strong presence in the market. name: Consumer Behavior\ntype: Concept\ndescription: Consumer behavior refers to the actions and decision-making processes of consumers in relation to purchasing and using goods and services. name: color psychology\ntype: Psychological Concept\ndescription: Color psychology is the study of how colors affect human behavior and perception. It is used by businesses to influence consumer perceptions. name: Competitors\ntype: Business Entities\ndescription: Competitors are other businesses that offer similar products or services in the same market. name: Marketing Strategies\ntype: Business Strategy\ndescription: Marketing strategies are comprehensive plans designed to achieve specific business objectives, such as increasing brand awareness, driving sales, and building customer loyalty. They often involve the use of color psychology to influence consumer behavior. name: green\ntype: Color\ndescription: Green is a color that evokes feelings of trust, reliability, and calmness. It can also create a sense of nature and growth. name: Perception of Value\ntype: Value Perception\ndescription: The perceived value associated with a product or service. name: Cultural and Contextual Associations\ntype: Concept\ndescription: Cultural and contextual associations refer to the meanings and perceptions of colors in different cultural and situational contexts. name: Brand Presence\ntype: Outcome\ndescription: The overall visibility and recognition of a brand among consumers. name: Color Meanings and Associations\ntype: Concept\ndescription: The meanings and associations of colors can vary significantly across different cultures. name: Nature and Growth\ntype: Concept\ndescription: The natural world, including plants, forests, and the environment. name: Brand Personality\ntype: Personality Trait\ndescription: The set of human characteristics attributed to a brand. name: Branding\ntype: Concept\ndescription: Branding refers to the practice of creating a name, symbol, or design that identifies and differentiates a product, service, or organization from its competitors. name: Distinctive Color Scheme\ntype: Attribute\ndescription: A unique combination of colors that sets a brand apart from its competitors. name: Brand Perception\ntype: Concept\ndescription: The overall impression that consumers have about a brand. name: Color\ntype: Concept\ndescription: Color plays a crucial role in branding and marketing strategies, as it has the power to evoke emotions, convey messages, and influence consumer behavior. Different colors have different meanings and are often associated with particular emotions or qualities. name: brand identity\ntype: Concept\ndescription: Brand identity refers to the visual and emotional representation of a brand, including its name, logo, colors, and other elements that distinguish it from competitors. It is crucial for creating a strong connection with the target audience. name: Target Audience\ntype: Audience Segment\ndescription: The target audience refers to the specific group of people that a business aims to reach and engage with through its marketing efforts, products, or services. name: Brand Value\ntype: Perception\ndescription: The way consumers perceive a brand\"s value can be influenced by the colors used in branding. name: Calmness\ntype: Emotion\ndescription: A feeling of peace and tranquility, often associated with relaxation and serenity. name: Messages\ntype: Message\ndescription: Information or ideas communicated to an audience. name: Business\ntype: Organization\ndescription: A business is an organization that engages in commercial, industrial, or professional activities. name: Perception of Quality\ntype: Quality Perception\ndescription: The perceived level of quality associated with a product or service. name: orange\ntype: Color\ndescription: Orange is a warm color that can create a sense of urgency and encourage impulse purchases. It is often associated with warmth, energy, and excitement. name: Color Psychology\ntype: Concept\ndescription: The study of how colors influence human behavior and emotions. name: Emotions\ntype: Concept\ndescription: Emotions are complex psychological states that involve subjective feelings, physiological responses, and expressive behaviors. In the context of branding and marketing, emotions play a crucial role in influencing consumer behavior and perceptions. name: Cultural Factors\ntype: Factor\ndescription: Elements that are influenced by the cultural background of a target audience, such as traditions, values, and beliefs. name: Brand Quality\ntype: Concept\ndescription: Brand quality refers to the overall perception of the excellence or superiority of a brand\"s products or services.",
    "evaluation": 1
  },
  {
    "correct_answer": "Youth-oriented brands may use bright and bold colors.",
    "retrieved_context": "name: Trust and Reliability\ntype: Emotion\ndescription: A feeling of trust and reliability, often associated with stability and dependability. name: Contextual Factors\ntype: Factor\ndescription: Elements that are influenced by the specific context in which a brand is presented, such as industry norms and market conditions. name: Desired Message\ntype: Concept\ndescription: The desired message is the specific communication or impression a brand aims to convey to its target audience. name: Visual Identity\ntype: Concept\ndescription: Visual identity refers to the visual elements of a brand, such as logos, colors, and typography, that help in creating a distinct image. name: Consumer Behavior\ntype: Concept\ndescription: Consumer behavior refers to the actions and decision-making processes of consumers in relation to purchasing and using goods and services. name: green\ntype: Color\ndescription: Green is a color that evokes feelings of trust, reliability, and calmness. It can also create a sense of nature and growth. name: Perception of Value\ntype: Value Perception\ndescription: The perceived value associated with a product or service. name: Blue\ntype: Color\ndescription: Blue is a primary color that is often associated with trust, reliability, and calmness. name: Brand Presence\ntype: Outcome\ndescription: The overall visibility and recognition of a brand among consumers. name: Nature and Growth\ntype: Concept\ndescription: The natural world, including plants, forests, and the environment. name: Branding\ntype: Concept\ndescription: Branding refers to the practice of creating a name, symbol, or design that identifies and differentiates a product, service, or organization from its competitors. name: Brand Personality\ntype: Personality Trait\ndescription: The set of human characteristics attributed to a brand. name: Young Consumers\ntype: Demographic Group\ndescription: Young consumers are typically individuals between the ages of 13 and 25 who are highly influenced by trends, social media, and peer opinions. name: Distinctive Color Scheme\ntype: Attribute\ndescription: A unique combination of colors that sets a brand apart from its competitors. name: Color\ntype: Concept\ndescription: Color plays a crucial role in branding and marketing strategies, as it has the power to evoke emotions, convey messages, and influence consumer behavior. Different colors have different meanings and are often associated with particular emotions or qualities. name: youth-oriented brand\ntype: Brand\ndescription: A youth-oriented brand targets young consumers and often uses bright, bold colors to appeal to this demographic. name: Brand Value\ntype: Perception\ndescription: The way consumers perceive a brand\"s value can be influenced by the colors used in branding. name: Calmness\ntype: Emotion\ndescription: A feeling of peace and tranquility, often associated with relaxation and serenity. name: Messages\ntype: Message\ndescription: Information or ideas communicated to an audience. name: Perception of Quality\ntype: Quality Perception\ndescription: The perceived level of quality associated with a product or service. name: orange\ntype: Color\ndescription: Orange is a warm color that can create a sense of urgency and encourage impulse purchases. It is often associated with warmth, energy, and excitement. name: Color Psychology\ntype: Concept\ndescription: The study of how colors influence human behavior and emotions. name: Cultural Factors\ntype: Factor\ndescription: Elements that are influenced by the cultural background of a target audience, such as traditions, values, and beliefs. name: Emotions\ntype: Concept\ndescription: Emotions are complex psychological states that involve subjective feelings, physiological responses, and expressive behaviors. In the context of branding and marketing, emotions play a crucial role in influencing consumer behavior and perceptions. name: Yellow\ntype: Color\ndescription: Yellow is a bright and cheerful color often associated with happiness, optimism, and energy. name: Brand Quality\ntype: Concept\ndescription: Brand quality refers to the overall perception of the excellence or superiority of a brand\"s products or services.",
    "evaluation": 1
  },
  {
    "accuracy": "100.00%"
  }
]